mvncrawler/__init__.py
mvncrawler/__main__.py
mvncrawler/crawler.py
mvncrawler-0.1.0.dist-info/LICENSE
mvncrawler-0.1.0.dist-info/METADATA
mvncrawler-0.1.0.dist-info/WHEEL
mvncrawler-0.1.0.dist-info/entry_points.txt
mvncrawler-0.1.0.dist-info/top_level.txt
mvncrawler-0.1.0.dist-info/RECORD
