Metadata-Version: 2.1
Name: mvncrawler
Version: 0.1.0
Summary: A crawler for extracting Maven coordinates
Home-page: https://github.com/fasten-project/mvn-crawler
Author: FASTEN project - Amir M. Mir
Author-email: mir-am@hotmail.com
License: UNKNOWN
Keywords: crawler maven coordinates fasten
Platform: UNKNOWN
Classifier: License :: OSI Approved :: Apache Software License
Classifier: Environment :: Console
Classifier: Programming Language :: Python
Classifier: Programming Language :: Python :: 3.5
Classifier: Programming Language :: Python :: 3.6
Classifier: Programming Language :: Python :: 3.7
Classifier: Operating System :: Unix
Classifier: Operating System :: MacOS
Classifier: Operating System :: POSIX
Classifier: Intended Audience :: Science/Research
Classifier: Topic :: Software Development
Requires-Dist: requests
Requires-Dist: beautifulsoup4
Requires-Dist: kafka-python
